Workbook

Sheet Unit prices
A1: The Tradeoff Method for ML Systems: cost-and-capacity toolkit
A2: Unit prices and per-accelerator capacities. Blue cells on yellow are inputs; edit them when prices move (checked September 2026). Every other tab reads from here. The book prints quantities and ratios only; this tab is where the money is.
A4: Name | B4: Item | C4: Value | D4: Unit | E4: Source / note
A5: CORE_H | B5: Core (vCPU) | C5: 0.04 | D5: $ per hour | E5: public list, Sept 2026
A6: ACC_RENT_H | B6: Accelerator, rented | C6: 2.5 | D6: $ per hour | E6: mid-range data-centre accelerator, on demand
A7: ACC_OWN_H | B7: Accelerator, owned, amortised at full use | C7: 0.9 | D7: $ per hour | E7: purchase + hosting over 3 years
A8: ACC_RATIO | B8: Accelerator-hour to core-hour | C8: 30 | D8: ratio | E8: Appendix A.9: 20–60×
A9: ACC_MEM | B9: Accelerator memory | C9: 80 | D9: GB | E9: Appendix A.3: 40–200
A10: ACC_BW | B10: Accelerator memory bandwidth | C10: 2 | D10: TB/s | E10: Appendix A.3: 1.5–8
A11: PREFILL | B11: Prefill throughput, mid-sized model | C11: 50000 | D11: tokens/s per accelerator | E11: Appendix A.3: 20k–100k
A12: DECODE | B12: Decode throughput, mid-sized model, batched | C12: 5000 | D12: tokens/s per accelerator | E12: Appendix A.3: 2k–10k
A13: KV | B13: Key–value state per token, mid-sized model | C13: 100000 | D13: bytes | E13: Appendix A.3: 50–200 KB
A14: RANKER_CORE | B14: Small ranker, one item, on a core | C14: 30 | D14: µs | E14: Appendix A.2: 20–50
A15: RANKER_ACC | B15: Small ranker, one item, batched on an accelerator | C15: 2 | D15: µs | E15: Appendix A.2: 1–2
A16: EMB_ACC | B16: Text embedding, one passage, batched | C16: 0.5 | D16: ms | E16: Appendix A.2: 0.3–1
... A19: TOK_IN | B19: Input tokens, rented | C19: 0.5 | D19: $ per million | E19: hosted mid-sized model
A20: TOK_IN_C | B20: Input tokens, cached prefix | C20: 0.1 | D20: $ per million
A21: TOK_OUT | B21: Output tokens, rented | C21: 2 | D21: $ per million
A22: OBJ | B22: Object storage | C22: 20 | D22: $ per TB-month
A23: MEM | B23: Memory in a serving node | C23: 8 | D23: $ per GB-month
A24: GRAPH_X | B24: Graph index memory, multiple of raw vectors | C24: 2.5 | D24: ratio | E24: Appendix A.5: 2–3×
A25: CLUSTER_X | B25: Cluster index memory, multiple of raw vectors | C25: 1.1 | D25: ratio | E25: Appendix A.5: ~1.1×
A26: JUDGE | B26: One human judgement | C26: 1 | D26: $ | E26: Chapter 5: cents to dollars
A27: REV_DAY | B27: Reviewer decisions per day | C27: 300 | D27: per person | E27: Chapter 12
A28: REV_H | B28: Reviewer, loaded | C28: 30 | D28: $ per hour | E28: Chapter 13, Exercise 2
A29: DAY_S | B29: Seconds in the book's day | C29: 100000 | D29: s | E29: 10^5

Sheet Fleet from a rate
A1: Fleet from a rate (Chapters 4, 7)
A2: Items scored per second × cost per item = core- or accelerator-seconds per second; divide by the target utilisation. Example: the recommender's ranker, 1,000 req/s × 2,000 candidates.
A4: Input | B4: Value | D4: Result | E4: Value
A5: Requests per second at peak | B5: 1000 | D5: Items per second | E5: =B5*B6
A6: Items scored per request | B6: 2000 | D6: Core-seconds per second | E6: =E5*B7/1000000
A7: Cost per item on a core (µs) | B7: 30 | D7: Cores at utilisation | E7: =ROUNDUP(E6/B9,0)
A8: Cost per item batched on an accelerator (µs) | B8: 2 | D8: Accelerator-seconds per second | E8: =E5*B8/1000000
A9: Target utilisation | B9: 0.7 | D9: Accelerators at utilisation | E9: =ROUNDUP(E8/B9,0)
D10: Core-seconds per thousand requests | E10: =B6*B7/1000000*1000
D11: Cores, $ per hour at utilisation | E11: =E6/B9*'Unit prices'!$C$5
D12: Accelerators, $ per hour rented | E12: =E9*'Unit prices'!$C$6

Sheet Generative serving
A1: Generative serving (Chapters 8, 13)
A2: Prefill is compute-bound; decode is memory-bound and the in-flight state caps the batch. Size the two pools separately and take the larger of decode-by-throughput and decode-by-memory. Example: the serving platform, 2,000 req/s.
A4: Input | B4: Value | D4: Result | E4: Value
A5: Requests per second at peak | B5: 2000 | D5: Prefill tokens per second, no cache | E5: =B5*B6
A6: Input tokens per request | B6: 4000 | D6: Prefill accelerators, no cache | E6: =ROUNDUP(E5/'Unit prices'!$C$11,0)
A7: Cached shared-prefix tokens | B7: 3000 | D7: Prefill tokens per second, cached | E7: =B5*(B6-B7)
A8: Output tokens per request | B8: 300 | D8: Prefill accelerators, cached | E8: =ROUNDUP(E7/'Unit prices'!$C$11,0)
A9: Seconds a request stays in flight | B9: 6 | D9: Decode tokens per second | E9: =B5*B8
A10: Model parameters (billions) | B10: 10 | D10: Decode accelerators by throughput | E10: =ROUNDUP(E9/'Unit prices'!$C$12,0)
A11: Bytes per parameter (2 half, 1 8-bit) | B11: 2 | D11: Model bytes (GB) | E11: =B10*B11
D12: Free memory per accelerator (GB) | E12: ='Unit prices'!$C$9-E11
D13: KV state per request (GB) | E13: =(B6+B8)*'Unit prices'!$C$13/1000000000
D14: Sequences in flight per accelerator | E14: =INT(E12/E13)
D15: Sequences in flight across the pool | E15: =B5*B9
D16: Decode accelerators by memory | E16: =ROUNDUP(E15/E14,0)
D17: Decode pool (the larger) | E17: =MAX(E10,E16)
D18: Total at peak, cached prefix | E18: =E8+E17
D19: Single-sequence decode rate (tokens/s) | E19: ='Unit prices'!$C$10*1000000000000/(E11*1000000000)
D20: Accelerator-seconds per request | E20: =(B6-B7)/'Unit prices'!$C$11+B8/'Unit prices'!$C$12
D21: Rented $ per thousand requests | E21: =((B6-B7)*'Unit prices'!$C$19+B7*'Unit prices'!$C$20+B8*'Unit prices'!$C$21)/1000000*1000
D22: Output tokens' share of the rented bill | E22: =(B8*'Unit prices'!$C$21)/((B6-B7)*'Unit prices'!$C$19+B7*'Unit prices'!$C$20+B8*'Unit prices'!$C$21)

Sheet Own vs rent
A1: Own against rent (Chapter 8)
A2: Owning is priced for peak and paid whether used or not; renting is paid for what is used. The break-even is a utilisation. Examples: the support assistant (2 accelerators at 7%) and the platform (160 at 40–70%).
A4: Input | B4: Value | D4: Result | E4: Value
A5: Accelerators at peak | B5: 160 | D5: Own, $ per year | E5: =B5*8760*'Unit prices'!$C$7
A6: Average utilisation over the day | B6: 0.4 | D6: Rent, $ per year | E6: =B5*B6*8760*'Unit prices'!$C$6
D7: Break-even utilisation | E7: ='Unit prices'!$C$7/'Unit prices'!$C$6
D8: Decision | E8: =IF(E5<E6,"own","rent")

Sheet Index and false matches
A1: Vectors, indexes and the false-match budget (Chapters 7, 12)
A2: Memory for N vectors at d dims and bytes per dim, under a graph or cluster index; and the per-pair false-match probability a threshold must deliver for a ceiling of wrongful matches a day, tested over K candidates. Example: near-duplicate search, 2B vectors.
A4: Input | B4: Value | D4: Result | E4: Value
A5: Vectors | B5: 2000000000 | D5: Raw vectors (GB) | E5: =B5*B6*B7/1000000000
A6: Dimensions | B6: 128 | D6: Graph index (GB) | E6: =E5*'Unit prices'!$C$24
A7: Bytes per dimension (4 fp32, 1 int8, 0.25 for 32-byte codes at 128 dims) | B7: 0.25 | D7: Cluster index (GB) | E7: =E5*'Unit prices'!$C$25
A8: Uploads (queries) per day | B8: 5000000 | D8: Cluster index, $ per month in memory | E8: =E7*'Unit prices'!$C$23
A9: Candidates the threshold is applied to | B9: 20 | D9: Per-pair false-match probability required | E9: =B10/(B8*B9)
A10: Ceiling on wrongful matches per day | B10: 100 | D10: Same, if applied over every vector | E10: =B10/(B8*B5)

Sheet Labels, logs, cadence
A1: Labels, logs and cadence (Chapters 5, 6, 9, 12)
A2: The served-feature log sized from the label delay; a retrain cadence priced; a judged set sized from the difference to detect; a prevalence sample sized from the precision wanted.
A4: Input | B4: Value | D4: Result | E4: Value
A5: Items served per second | B5: 10000 | D5: Log retention (days) | E5: =B7+B8
A6: Bytes per served-feature row | B6: 800 | D6: Log, GB per day | E6: =B5*'Unit prices'!$C$29*B6/1000000000
A7: Label delay (days) | B7: 90 | D7: Log, TB total | E7: =E6*E5/1000
A8: Training window (days) | B8: 90 | D8: Log, $ per month in object storage | E8: =E7*'Unit prices'!$C$22
A9: Retrain: hours per run | B9: 300 | D9: Retrain, $ per day | E9: =B9*B10*IF(B11=1,'Unit prices'!$C$6,'Unit prices'!$C$5)
A10: Retrain: runs per day | B10: 1 | D10: Retrain, $ per year | E10: =E9*365
A11: Retrain on accelerators? (1 yes, 0 no) | B11: 0 | D11: Judged set size n | E11: =ROUNDUP(4*B12*(1-B12)/B13^2,0)
A12: Judged set: rate being measured p | B12: 0.9 | D12: Judged set, $ at the human rate | E12: =E11*'Unit prices'!$C$26
A13: Judged set: difference to detect | B13: 0.02 | D13: Prevalence sample, views per week | E13: =ROUNDUP(1.96^2*(1-B14)/(B15^2*B14),0)
A14: Prevalence being measured | B14: 0.0005 | D14: Reviewers, full time | E14: =E13/7/'Unit prices'!$C$27
A15: Relative half-width wanted | B15: 0.2
