Workbook

Sheet Unit prices
A1: The Tradeoff Method: capacity toolkit
A2: Unit prices and per-node capacities. Blue cells are inputs; edit them when cloud pricing moves (checked September 2026). Every other tab reads from here.
A4: Item | B4: Value | C4: Unit | D4: Source / note
A5: Seconds in a day (the book rounds 86,400 to 10^5) | B5: 100000 | C5: s | D5: Chapter 4, seven habits
A6: Object storage, standard | B6: 20 | C6: $ per TB-month | D6: Appendix A.4; public list prices, Sept 2026
A7: Object storage, cold tier | B7: 6 | C7: $ per TB-month | D7: Appendix A.4
A8: Block storage attached to a node | B8: 90 | C8: $ per TB-month | D8: Appendix A.4
A9: Memory in a managed cache | B9: 8 | C9: $ per GB-month | D9: Appendix A.4
A10: Virtual CPU | B10: 0.04 | C10: $ per hour | D10: Appendix A.4
A11: Small always-on server | B11: 100 | C11: $ per month | D11: Appendix A.4
A12: Managed database node, mid-sized | B12: 500 | C12: $ per month | D12: Appendix A.4 (a few hundred)
A13: Managed database node, large | B13: 3000 | C13: $ per month | D13: Appendix A.4 (a few thousand)
A14: Egress to the internet, list | B14: 0.05 | C14: $ per GB | D14: Appendix A.4; the book uses the low end
A15: Egress through a CDN, negotiated | B15: 0.02 | C15: $ per GB | D15: Appendix A.4
A16: Traffic between regions | B16: 0.015 | C16: $ per GB | D16: Appendix A.4
... A29: Round trip, across an ocean | B29: 120 | C29: ms | D29: Appendix A.1

Sheet Envelope
A1: Envelope: rate, stored, moved, cost
A2: Fill the blue cells for your brief. The example values are the notification service of Chapters 3 and 4; replace them.
A4: Input | B4: Value | C4: Unit | D4: Note
A5: Daily active users | B5: 20000000 | C5: users
A6: Actions per user per day | B6: 5 | C6: actions
A7: Peak multiple over average | B7: 5 | C7: x
A8: Bytes per event stored | B8: 200 | C8: bytes
A9: Retention | B9: 30 | C9: days
A10: Replicas | B10: 1 | C10: copies
A11: Bytes returned per request | B11: 1000 | C11: bytes
A12: Burst: total events | B12: 20000000 | C12: events
A13: Burst: window | B13: 600 | C13: seconds
A15: Output | B15: Value | C15: Unit | D15: Formula reads
A16: Average rate | B16: =B5*B6/'Unit prices'!$B$5 -> 1000 | C16: per second | D16: users x actions / 10^5
A17: Peak rate | B17: =B16*B7 -> 5000 | C17: per second | D17: average x peak multiple
A18: Burst rate | B18: =B12/B13 -> 33333.333 | C18: per second | D18: burst total / window
A19: Events per day | B19: =B5*B6 -> 100000000 | C19: events
A20: Stored at end of retention | B20: =B19*B8*B9*B10/1000000000000 -> 0.6 | C20: TB | D20: events/day x bytes x days x replicas
A21: Storage cost, object | B21: =B20*'Unit prices'!$B$6 -> 12 | C21: $ per month | D21: TB x object price
A22: Storage cost, block | B22: =B20*'Unit prices'!$B$8 -> 54 | C22: $ per month | D22: TB x block price
A23: Nodes by disk | B23: =CEILING(B20/'Unit prices'!$B$26,1) -> 1 | C23: nodes | D23: TB / usable disk per node
A24: Moved out, average | B24: =B16*B11 -> 1000000 | C24: bytes per second | D24: rate x bytes returned
A25: Moved out per day | B25: =B24*'Unit prices'!$B$5/1000000000 -> 100 | C25: GB per day
A26: Egress per day, list | B26: =B25*'Unit prices'!$B$14 -> 5 | C26: $ per day
A27: Egress per day, CDN | B27: =B25*'Unit prices'!$B$15 -> 2 | C27: $ per day
A28: Relational nodes for peak writes | B28: =CEILING(B17/'Unit prices'!$B$23,1) -> 1 | C28: nodes | D28: peak / writes per node
A29: LSM nodes for peak appends | B29: =CEILING(B17/'Unit prices'!$B$24,1) -> 1 | C29: nodes
A30: In-memory nodes for peak ops | B30: =CEILING(B17/'Unit prices'!$B$25,1) -> 1 | C30: nodes
A32: Binds: compare each output to the per-node figures on the Unit prices tab; the line closest to or beyond one node's capacity is the one that sets the design (Chapter 4).

Sheet Latency budget
A1: Latency budget splitter and fan-out tail
A2: Enter the total budget and the hops in sequence. Headroom is what is left for the tail. The example is Chapter 4's 200 ms page.
A4: Total budget (ms) | B4: 200
A6: Hop (sequential) | B6: ms | C6: Note
A7: User's network to the edge | B7: 35 | C7: outside your control; 20-50 ms
A8: Application server work | B8: 10
A9: Cache | B9: 1
A10: Database on a miss | B10: 10
A11: Downstream service | B11: 50 | C11: the largest item; a second sequential call breaks the budget
B12: 0
B13: 0
A15: Allocated (ms) | B15: =SUM(B7:B13) -> 106
A16: Headroom for the tail (ms) | B16: =B4-B15 -> 94
A17: Largest hop (ms) | B17: =MAX(B7:B13) -> 50
A18: A second sequential call to the largest hop breaks the budget? | B18: =IF(B15+B17>B4,"yes: make it parallel","no") -> no
A21: Fan-out tail
A22: Services called in parallel (n) | B22: 10
A23: Chance each is slow | B23: 0.01
A24: Chance the whole request is slow: 1-(1-p)^n | B24: =1-(1-B23)^B22 -> 0.095617925
A26: Chain availability
A27: Components in a synchronous chain | B27: 5
A28: Availability of each | B28: 0.999
A29: Availability of the chain | B29: =B28^B27 -> 0.99500999

Sheet Cost per thousand
A1: Cost per thousand requests, and the people line
A2: The example is Chapter 4's thumbnail service: 50 ms of CPU, a 20 KB image kept a year, served once.
A4: Input | B4: Value | C4: Unit
A5: CPU per request | B5: 50 | C5: ms
A6: Bytes stored per request | B6: 20000 | C6: bytes
A7: Retention | B7: 12 | C7: months
A8: Bytes returned per request | B8: 20000 | C8: bytes
A9: Served through a CDN? (1 yes, 0 no) | B9: 0 | C9: flag
A11: Term | B11: $ per 1,000 requests | C11: Reads
A12: Compute | B12: =B5/1000/3600*'Unit prices'!$B$10*1000 -> 0.00055555556 | C12: CPU seconds x vCPU price
A13: Storage | B13: =B6/1000000000000*'Unit prices'!$B$6*B7*1000 -> 0.0048 | C13: bytes x object price x months
A14: Egress | B14: =B8/1000000000*IF(B9=1,'Unit prices'!$B$15,'Unit prices'!$B$14)*1000 -> 0.001 | C14: bytes x egress price
A15: Total | B15: =SUM(B12:B14) -> 0.0063555556
A16: Dominant term | B16: =INDEX(A12:A14,MATCH(MAX(B12:B14),B12:B14,0)) -> Storage
A19: People (Chapter 11)
A20: Engineer hours a year the component consumes | B20: 150
A21: Cost per year | B21: =B20*'Unit prices'!$B$20 -> 15000
A22: Cost per month | B22: =B21/12 -> 1250
A24: Chapter 11's broker example: 150 hours a year is about $1,250 a month, against a $4,000 machine saving; the incidents are the missing term.

Sheet Backlog
A1: Backlog and drain (Chapter 10)
A2: The example is the notification burst: 33,000/s arriving for 600 s against 14,000/s of provider capacity.
A4: Input | B4: Value | C4: Unit
A5: Arrival rate during the burst | B5: 33000 | C5: per second
A6: Service rate | B6: 14000 | C6: per second
A7: Burst duration | B7: 600 | C7: seconds
A8: Arrival rate after the burst | B8: 0 | C8: per second
A9: Bytes per queued item | B9: 500 | C9: bytes
A10: Little's law: arrival rate | B10: 5000 | C10: per second
A11: Little's law: time each item spends inside | B11: 0.12 | C11: seconds
A13: Output | B13: Value | C13: Unit
A14: Peak queue depth | B14: =MAX(0,(B5-B6)*B7) -> 11400000 | C14: items
A15: Queue storage at peak | B15: =B14*B9/1000000000 -> 5.7 | C15: GB
A16: Drain time after the burst | B16: =IF(B6<=B8,"never: service does not exceed arrivals",B14/(B6-B8)/60) -> 13.571429 | C16: minutes
A17: Total time from burst start to empty | B17: =IF(B6<=B8,"never",B7/60+B16) -> 23.571429 | C17: minutes
A18: Items in the system (Little's law) | B18: =B10*B11 -> 600 | C18: items
A19: Workers needed at that service time | B19: =B10*B11 -> 600 | C19: workers
A21: A backlog drains at the margin of service over arrivals, not at the service rate: doubling capacity does not halve the drain (Chapter 10).
